PyWebTools-1.1.3.dist-info/DESCRIPTION.rst
PyWebTools-1.1.3.dist-info/LICENSE.txt
PyWebTools-1.1.3.dist-info/METADATA
PyWebTools-1.1.3.dist-info/RECORD
PyWebTools-1.1.3.dist-info/WHEEL
PyWebTools-1.1.3.dist-info/entry_points.txt
PyWebTools-1.1.3.dist-info/metadata.json
PyWebTools-1.1.3.dist-info/top_level.txt
pywebtools/__init__.py
pywebtools/formencode.py
pywebtools/sqlalchemy.py
pywebtools/testing.py
pywebtools/kajiki/__init__.py
pywebtools/kajiki/form.kajiki
pywebtools/kajiki/menu.kajiki
pywebtools/kajiki/navigation.kajiki
pywebtools/pyramid/__init__.py
pywebtools/pyramid/decorators.py
pywebtools/pyramid/util.py
pywebtools/pyramid/auth/__init__.py
pywebtools/pyramid/auth/decorators.py
pywebtools/pyramid/auth/models.py
pywebtools/pyramid/auth/views.py
