Metadata-Version: 2.0
Name: PyWebTools
Version: 1.1.3
Summary: A collection of helpers for use with Pyramid, Kajiki, Formencode, and SQLAlchemy
Home-page: http://bitbucket.org/mhall/pywebtools/overview
Author: Mark Hall
Author-email: Mark.Hall@work.room3b.eu
License: UNKNOWN
Keywords: web pyramid kajiki formencode SQLAlchemy
Platform: UNKNOWN
Classifier: Development Status :: 4 - Beta
Classifier: Programming Language :: Python :: 3
Classifier: Topic :: Internet :: WWW/HTTP
Classifier: Topic :: Software Development :: Libraries :: Python Modules
Classifier: Intended Audience :: Developers
Classifier: License :: OSI Approved :: GNU Lesser General Public License v3 or later (LGPLv3+)
Classifier: Operating System :: OS Independent
Requires-Dist: kajiki
Requires-Dist: sqlalchemy
Requires-Dist: formencode
Requires-Dist: pyramid
Requires-Dist: decorator
Requires-Dist: transaction
Requires-Dist: zope.sqlalchemy
Provides-Extra: testing
Requires-Dist: WebTest (>=1.3.1); extra == 'testing'
Requires-Dist: pytest; extra == 'testing'
Requires-Dist: pytest-cov; extra == 'testing'
